commonlib/__init__.py
commonlib/confighttp.py
commonlib/connectdb.py
commonlib/htmlresult.py
commonlib/sendemail.py
lyhapi-0.0.11.dist-info/METADATA
lyhapi-0.0.11.dist-info/WHEEL
lyhapi-0.0.11.dist-info/top_level.txt
lyhapi-0.0.11.dist-info/RECORD
