Metadata-Version: 2.1
Name: lyhapi
Version: 0.0.11
Summary: lyhcc information retriver
Home-page: https://github.com/vissyzhu/lyhapi.git
Author: vissyzhu
Author-email: 1209354095@qq.com
License: MIT
Platform: UNKNOWN
